{
    "01": {
        "id" : "1",
        "title": "ナチュラル",
        "background": "back_001.png",
        "mask": "none",
        "filter": "CISepiaTone",
        "x": "20",
        "y": "30",
        "width": "200",
        "rotate" : "0",
        "square" : "false",
        "frame"  : "INSTANT",
        "deco1_image" : "leave_001.png",
        "deco1_pos_x" : "20",
        "deco1_pos_y" : "10",
        "deco1_scale" : "100",
        "deco1_rotate" : "10",
        "deco2_image" : "",
        "deco2_pos_x" : "",
        "deco2_pos_y" : "",
        "deco2_scale" : "",
        "deco2_rotate" : "",
        "deco3_image" : "",
        "deco3_pos_x" : "",
        "deco3_pos_y" : "",
        "deco3_scale" : "",
        "deco3_rotate" : ""
    },
    "02": {
        "id" : "2",
        "title": "ナチュラル",
        "background": "back_001.png",
        "mask": "none",
        "filter": "CIPhotoEffectInstant",
        "x": "150",
        "y": "120",
        "width": "200",
        "rotate" : "0",
        "square" : "false",
        "frame"  : "INSTANT",
        "deco1_image" : "leave_002.png",
        "deco1_pos_x" : "50",
        "deco1_pos_y" : "10",
        "deco1_scale" : "100",
        "deco1_rotate" : "10",
        "deco2_image" : "",
        "deco2_pos_x" : "",
        "deco2_pos_y" : "",
        "deco2_scale" : "",
        "deco2_rotate" : "",
        "deco3_image" : "",
        "deco3_pos_x" : "",
        "deco3_pos_y" : "",
        "deco3_scale" : "",
        "deco3_rotate" : ""
    },
    "03": {
        "id" : "3",
        "title": "ナチュラル",
        "background": "back_001.png",
        "mask": "none",
        "filter": "CIPhotoEffectInstant",
        "x": "50",
        "y": "220",
        "width": "240",
        "rotate" : "0",
        "square" : "false",
        "frame"  : "INSTANT",
        "deco1_image" : "leave_003.png",
        "deco1_pos_x" : "10",
        "deco1_pos_y" : "10",
        "deco1_scale" : "100",
        "deco1_rotate" : "-10",
        "deco2_image" : "",
        "deco2_pos_x" : "",
        "deco2_pos_y" : "",
        "deco2_scale" : "",
        "deco2_rotate" : "",
        "deco3_image" : "",
        "deco3_pos_x" : "",
        "deco3_pos_y" : "",
        "deco3_scale" : "",
        "deco3_rotate" : ""
    },
    "04": {
        "id" : "4",
        "title": "ナチュラル",
        "background": "back_001.png",
        "mask": "none",
        "filter": "CIPhotoEffectInstant",
        "x": "20",
        "y": "300",
        "width": "220",
        "rotate" : "-20",
        "square" : "false",
        "frame"  : "INSTANT",
        "deco1_image" : "leave_004.png",
        "deco1_pos_x" : "10",
        "deco1_pos_y" : "90",
        "deco1_scale" : "100",
        "deco1_rotate" : "20",
        "deco2_image" : "",
        "deco2_pos_x" : "",
        "deco2_pos_y" : "",
        "deco2_scale" : "",
        "deco2_rotate" : "",
        "deco3_image" : "",
        "deco3_pos_x" : "",
        "deco3_pos_y" : "",
        "deco3_scale" : "",
        "deco3_rotate" : ""
    },
    "05": {
        "id" : "5",
        "title": "ナチュラル",
        "background": "back_001.png",
        "mask": "none",
        "filter": "CISepiaTone",
        "x": "180",
        "y": "350",
        "width": "280",
        "rotate" : "10",
        "square" : "false",
        "frame"  : "INSTANT",
        "deco1_image" : "leave_005.png",
        "deco1_pos_x" : "10",
        "deco1_pos_y" : "40",
        "deco1_scale" : "100",
        "deco1_rotate" : "-30",
        "deco2_image" : "",
        "deco2_pos_x" : "",
        "deco2_pos_y" : "",
        "deco2_scale" : "",
        "deco2_rotate" : "",
        "deco3_image" : "",
        "deco3_pos_x" : "",
        "deco3_pos_y" : "",
        "deco3_scale" : "",
        "deco3_rotate" : ""
    },
    "06": {
        "id" : "6",
        "title": "ナチュラル",
        "background": "back_001.png",
        "mask": "none",
        "filter": "CIPhotoEffectInstant",
        "x": "10",
        "y": "400",
        "width": "180",
        "rotate" : "-20",
        "square" : "false",
        "frame"  : "INSTANT",
        "deco1_image" : "leave_001.png",
        "deco1_pos_x" : "80",
        "deco1_pos_y" : "80",
        "deco1_scale" : "100",
        "deco1_rotate" : "0",
        "deco2_image" : "",
        "deco2_pos_x" : "",
        "deco2_pos_y" : "",
        "deco2_scale" : "",
        "deco2_rotate" : "",
        "deco3_image" : "",
        "deco3_pos_x" : "",
        "deco3_pos_y" : "",
        "deco3_scale" : "",
        "deco3_rotate" : ""
    },
    "07": {
        "id" : "7",
        "title": "ナチュラル",
        "background": "back_001.png",
        "mask": "none",
        "filter": "CISepiaTone",
        "x": "200",
        "y": "10",
        "width": "100",
        "rotate" : "10",
        "square" : "true",
        "frame"  : "INSTANT",
        "deco1_image" : "leave_002.png",
        "deco1_pos_x" : "10",
        "deco1_pos_y" : "90",
        "deco1_scale" : "100",
        "deco1_rotate" : "10",
        "deco2_image" : "",
        "deco2_pos_x" : "",
        "deco2_pos_y" : "",
        "deco2_scale" : "",
        "deco2_rotate" : "",
        "deco3_image" : "",
        "deco3_pos_x" : "",
        "deco3_pos_y" : "",
        "deco3_scale" : "",
        "deco3_rotate" : ""
    },
    "08": {
        "id" : "8",
        "title": "ナチュラル",
        "background": "back_001.png",
        "mask": "none",
        "filter": "CISepiaTone",
        "x": "280",
        "y": "60",
        "width": "120",
        "rotate" : "10",
        "square" : "true",
        "frame"  : "INSTANT",
        "deco1_image" : "leave_003.png",
        "deco1_pos_x" : "30",
        "deco1_pos_y" : "10",
        "deco1_scale" : "100",
        "deco1_rotate" : "30",
        "deco2_image" : "",
        "deco2_pos_x" : "",
        "deco2_pos_y" : "",
        "deco2_scale" : "",
        "deco2_rotate" : "",
        "deco3_image" : "",
        "deco3_pos_x" : "",
        "deco3_pos_y" : "",
        "deco3_scale" : "",
        "deco3_rotate" : ""
    },
    "09": {
        "id" : "9",
        "title": "ナチュラル",
        "background": "back_001.png",
        "mask": "none",
        "filter": "none",
        "x": "250",
        "y": "80",
        "width": "80",
        "rotate" : "1",
        "square" : "true",
        "frame"  : "INSTANT",
        "deco1_image" : "leave_004.png",
        "deco1_pos_x" : "80",
        "deco1_pos_y" : "10",
        "deco1_scale" : "100",
        "deco1_rotate" : "-20",
        "deco2_image" : "",
        "deco2_pos_x" : "",
        "deco2_pos_y" : "",
        "deco2_scale" : "",
        "deco2_rotate" : "",
        "deco3_image" : "",
        "deco3_pos_x" : "",
        "deco3_pos_y" : "",
        "deco3_scale" : "",
        "deco3_rotate" : ""
    },
}